arknights/__init__.py
arknights/ak.py
arknights/cgi.py
arknights/exception.py
arknights-0.1.11.dist-info/LICENSE
arknights-0.1.11.dist-info/WHEEL
arknights-0.1.11.dist-info/METADATA
arknights-0.1.11.dist-info/RECORD
